hellosign_sdk/__init__.py
hellosign_sdk/hsclient.py
hellosign_sdk/resource/__init__.py
hellosign_sdk/resource/account.py
hellosign_sdk/resource/embedded.py
hellosign_sdk/resource/resource.py
hellosign_sdk/resource/resource_list.py
hellosign_sdk/resource/signature.py
hellosign_sdk/resource/signature_request.py
hellosign_sdk/resource/team.py
hellosign_sdk/resource/template.py
hellosign_sdk/resource/unclaimed_draft.py
hellosign_sdk/utils/__init__.py
hellosign_sdk/utils/exception.py
hellosign_sdk/utils/hsaccesstokenauth.py
hellosign_sdk/utils/hsformat.py
hellosign_sdk/utils/request.py
hellosign_python_sdk_custom-1.dist-info/LICENSE
hellosign_python_sdk_custom-1.dist-info/METADATA
hellosign_python_sdk_custom-1.dist-info/WHEEL
hellosign_python_sdk_custom-1.dist-info/top_level.txt
hellosign_python_sdk_custom-1.dist-info/RECORD
