Metadata-Version: 2.1
Name: hellosign-python-sdk-custom
Version: 1
Summary: A Python wrapper for the HelloSign API with some custom changes (http://www.hellosign.com/api)
Home-page: https://github.com/HelloFax/hellosign-python-sdk
Author: HelloSign
Author-email: apisupport@hellosign.com
License: MIT
Keywords: hellosign python sdk
Platform: UNKNOWN
Classifier: Development Status :: 5 - Production/Stable
Classifier: License :: OSI Approved :: MIT License
Classifier: Programming Language :: Python :: 2.7
Requires-Dist: requests
